resolveRID.py
timeroast_ng-0.1.dev0.data/scripts/resolveRID.py
timeroast_ng-0.1.dev0.data/scripts/timeroast-ng.py
timeroast_ng-0.1.dev0.dist-info/LICENSE
timeroast_ng-0.1.dev0.dist-info/METADATA
timeroast_ng-0.1.dev0.dist-info/WHEEL
timeroast_ng-0.1.dev0.dist-info/top_level.txt
timeroast_ng-0.1.dev0.dist-info/RECORD
