Metadata-Version: 2.2
Name: timeroast_ng
Version: 0.1.dev0
Summary: Implementation of the Timeroasting attack to grab hashes from computer accounts using SNTP-MS.
Home-page: https://github.com/MatrixEditor/timeroast-ng
Author: MatrixEditor
License: MIT
Platform: Unix
Platform: Windows
Classifier: Programming Language :: Python :: 3.13
Classifier: Programming Language :: Python :: 3.12
Classifier: Programming Language :: Python :: 3.11
Classifier: Programming Language :: Python :: 3.10
License-File: LICENSE
Requires-Dist: impacket
Requires-Dist: rich
Dynamic: author
Dynamic: classifier
Dynamic: description
Dynamic: description-content-type
Dynamic: home-page
Dynamic: license
Dynamic: platform
Dynamic: requires-dist
Dynamic: summary
